LICENSE
setup.py
ohi_latex/__init__.py
ohi_latex/__main__.py
ohi_latex.egg-info/PKG-INFO
ohi_latex.egg-info/SOURCES.txt
ohi_latex.egg-info/dependency_links.txt
ohi_latex.egg-info/entry_points.txt
ohi_latex.egg-info/top_level.txt